X600_ATE_JIRA_Interaction_test/X600_ATE_JIRA_Interaction_test.py
X600_ATE_JIRA_Interaction_test/__init__.py
X600_ATE_JIRA_Interaction_test-0.0.1.dist-info/METADATA
X600_ATE_JIRA_Interaction_test-0.0.1.dist-info/WHEEL
X600_ATE_JIRA_Interaction_test-0.0.1.dist-info/top_level.txt
X600_ATE_JIRA_Interaction_test-0.0.1.dist-info/RECORD
