Metadata-Version: 2.1
Name: X600-ATE-JIRA-Interaction-test
Version: 0.0.1
Summary: Allow interaction between ATE and JIRA
Author: Houssem Eddine Amor
Author-email: <youremail@email.com>
Keywords: python,first package
Classifier: Development Status :: 3 - Alpha
Classifier: Intended Audience :: Education
Classifier: Programming Language :: Python :: 2
Classifier: Programming Language :: Python :: 3
Classifier: Operating System :: MacOS :: MacOS X
Classifier: Operating System :: Microsoft :: Windows
